{
  "posts": [
    {
      "id": 1,
      "title": "json-server",
      "author": "typicode"
    }
  ],
  "comments": [
    {
      "id": 1,
      "body": "some comment",
      "postId": 1
    }
  ],
  "profile": {
    "name": "typicode"
  },
  "conselho": [
    {
      "nome": "testeasdfasdf",
      "ultimaAlteracao": "aaaaaasdfasdf",
      "id": 14
    },
    {
      "nome": "testeasdfasdf",
      "ultimaAlteracao": "aaaaaasdfasdf",
      "id": 16
    },
    {
      "nome": "testeasdfasdf",
      "ultimaAlteracao": "aaaaaasdfasdfaa",
      "id": 17
    },
    {
      "nome": "testeasdfasdf",
      "ultimaAlteracao": "aaaaaasdfasdf",
      "id": 18
    },
    {
      "nome": "qqq",
      "ultimaAlteracao": "123123",
      "id": 19
    }
  ],
  "paciente": [
    {
      "id": 1,
      "nome": "Rafaelss",
      "dataNascimento": "28/02/1990",
      "cep": "89225-677",
      "cidade": "Joinville",
      "bairro": "Aventureiro",
      "rua": "Rua Aristídes da Veiga Coutinho",
      "numero": "119",
      "cpf": "096.691.639-51"
    },
    {
      "cep": "89225677",
      "nome": "mateus",
      "bairro": "Aventureiro",
      "cidade": "Joinville",
      "rua": "Rua Aristídes da Veiga Coutinho",
      "numero": "123",
      "dataNascimento": "28/07/1997",
      "cpf": "096.691.639-51",
      "id": 2
    },
    {
      "cep": "89225-815",
      "nome": "Matheus",
      "bairro": "Aventureiro",
      "cidade": "Joinville",
      "rua": "Rua Ivani Ribeiro",
      "numero": "89",
      "dataNascimento": "23/09/2000",
      "cpf": "123.121.323-32",
      "id": 3
    }
  ],
  "login": [
    {
      "id": 1,
      "usuario": "rafael",
      "senha": "00000000"
    },
    {
      "id": 2,
      "usuario": "teste",
      "senha": "12345678"
    }
  ]
}